mstsc/__init__.py
mstsc/security.py
mstsc-1.0.0.dist-info/LICENSE
mstsc-1.0.0.dist-info/METADATA
mstsc-1.0.0.dist-info/WHEEL
mstsc-1.0.0.dist-info/top_level.txt
mstsc-1.0.0.dist-info/RECORD
